<?xml version="1.0" encoding="utf-8" ?>
<dwsync>
<file name="Admin.php" server="ftp.empleosccb.com.mx" local="131733529896790023" remote="131538132000000000" Dst="2" />
<file name="Gruntfile.js" server="ftp.empleosccb.com.mx" local="131733530213022193" remote="131036148000000000" Dst="2" />
<file name="LICENSE" server="ftp.empleosccb.com.mx" local="131733530213334304" remote="131036148000000000" Dst="2" />
<file name="README.md" server="ftp.empleosccb.com.mx" local="131733530238224694" remote="131036148000000000" Dst="2" />
<file name="bower.json" server="ftp.empleosccb.com.mx" local="131733530321492580" remote="131036148000000000" Dst="2" />
<file name="composer.json" server="ftp.empleosccb.com.mx" local="131733530754839988" remote="131036148000000000" Dst="2" />
<file name="changelog" server="ftp.empleosccb.com.mx" local="131733530755783606" remote="131036148000000000" Dst="2" />
<file name="error_log" server="ftp.empleosccb.com.mx" local="131733531049543123" remote="131733333600000000" Dst="2" />
<file name="index.php" server="ftp.empleosccb.com.mx" local="131733531076746957" remote="131706028800000000" Dst="2" />
<file name="index1.html" server="ftp.empleosccb.com.mx" local="131733531081172019" remote="131036148000000000" Dst="2" />
<file name="index2.html" server="ftp.empleosccb.com.mx" local="131733531084928652" remote="131588421000000000" Dst="2" />
<file name="package.json" server="ftp.empleosccb.com.mx" local="131733531101860423" remote="131036148000000000" Dst="2" />
<file name="starter.html" server="ftp.empleosccb.com.mx" local="131733533809467239" remote="131036148000000000" Dst="2" />
<file name="public_html.zip" server="ftp.empleosccb.com.mx" local="131733533814668488" remote="131721058800000000" Dst="2" />
</dwsync>